sknnr/__about__.py
sknnr/__init__.py
sknnr/_base.py
sknnr/_euclidean.py
sknnr/_gnn.py
sknnr/_mahalanobis.py
sknnr/_msn.py
sknnr/_rfnn.py
sknnr/datasets/__init__.py
sknnr/datasets/_base.py
sknnr/datasets/data/__init__.py
sknnr/datasets/data/moscow_env.csv
sknnr/datasets/data/moscow_spp.csv
sknnr/datasets/data/swo_ecoplot_env.csv
sknnr/datasets/data/swo_ecoplot_spp.csv
sknnr/transformers/__init__.py
sknnr/transformers/_base.py
sknnr/transformers/_cca.py
sknnr/transformers/_cca_transformer.py
sknnr/transformers/_ccora.py
sknnr/transformers/_ccora_transformer.py
sknnr/transformers/_mahalanobis_transformer.py
sknnr/transformers/_rfnode_transformer.py
sknnr-0.1.0a3.dist-info/METADATA
sknnr-0.1.0a3.dist-info/WHEEL
sknnr-0.1.0a3.dist-info/RECORD
