Metadata-Version: 2.4
Name: sknnr
Version: 0.1.0a3
Summary: Scikit-learn estimators for kNN regression methods
Project-URL: Homepage, https://github.com/lemma-osu/sknnr
Project-URL: Source, https://github.com/lemma-osu/sknnr
Author-email: Matt Gregory <matt.gregory@oregonstate.edu>, Aaron Zuspan <aaron.zuspan@oregonstate.edu>
Requires-Python: >=3.9
Requires-Dist: numpy
Requires-Dist: scikit-learn>=1.2
Requires-Dist: scipy
